[
  {
    "ContainingType": "BookMyShowBackend.Controllers.BookMyShowController",
    "Method": "Login",
    "RelativePath": "api/auth/login",
    "HttpMethod": "POST",
    "IsController": true,
    "Order": 0,
    "Parameters": [
      {
        "Name": "dto",
        "Type": "BookMyShowBackend.DTO.LogInDTO",
        "IsRequired": true
      }
    ],
    "ReturnTypes": []
  },
  {
    "ContainingType": "BookMyShowBackend.Controllers.BookMyShowController",
    "Method": "Register",
    "RelativePath": "api/auth/register",
    "HttpMethod": "POST",
    "IsController": true,
    "Order": 0,
    "Parameters": [
      {
        "Name": "dto",
        "Type": "BookMyShowBackend.Models.Users",
        "IsRequired": true
      }
    ],
    "ReturnTypes": []
  },
  {
    "ContainingType": "BookMyShowBackend.Controllers.BookMyShowController",
    "Method": "GetAllBookings",
    "RelativePath": "api/bookings",
    "HttpMethod": "GET",
    "IsController": true,
    "Order": 0,
    "Parameters": [],
    "ReturnTypes": []
  },
  {
    "ContainingType": "BookMyShowBackend.Controllers.BookMyShowController",
    "Method": "GetBookingsById",
    "RelativePath": "api/bookings/{id}",
    "HttpMethod": "GET",
    "IsController": true,
    "Order": 0,
    "Parameters": [
      {
        "Name": "id",
        "Type": "System.Int32",
        "IsRequired": true
      }
    ],
    "ReturnTypes": []
  },
  {
    "ContainingType": "BookMyShowBackend.Controllers.BookMyShowController",
    "Method": "GetAllMovies",
    "RelativePath": "api/movies",
    "HttpMethod": "GET",
    "IsController": true,
    "Order": 0,
    "Parameters": [
      {
        "Name": "genre",
        "Type": "System.String",
        "IsRequired": false
      }
    ],
    "ReturnTypes": []
  },
  {
    "ContainingType": "BookMyShowBackend.Controllers.BookMyShowController",
    "Method": "GetMovieById",
    "RelativePath": "api/movies/{id}",
    "HttpMethod": "GET",
    "IsController": true,
    "Order": 0,
    "Parameters": [
      {
        "Name": "id",
        "Type": "System.Int32",
        "IsRequired": true
      }
    ],
    "ReturnTypes": []
  },
  {
    "ContainingType": "BookMyShowBackend.Controllers.BookMyShowController",
    "Method": "CreateMovie",
    "RelativePath": "api/movies/create",
    "HttpMethod": "POST",
    "IsController": true,
    "Order": 0,
    "Parameters": [
      {
        "Name": "movie",
        "Type": "BookMyShowBackend.Models.Movie",
        "IsRequired": true
      }
    ],
    "ReturnTypes": []
  },
  {
    "ContainingType": "BookMyShowBackend.Controllers.BookMyShowController",
    "Method": "DeleteMovie",
    "RelativePath": "api/movies/delete/{id}",
    "HttpMethod": "DELETE",
    "IsController": true,
    "Order": 0,
    "Parameters": [
      {
        "Name": "id",
        "Type": "System.Int32",
        "IsRequired": true
      }
    ],
    "ReturnTypes": []
  },
  {
    "ContainingType": "BookMyShowBackend.Controllers.BookMyShowController",
    "Method": "DeleteShow",
    "RelativePath": "api/movies/slot/delete/{id}",
    "HttpMethod": "DELETE",
    "IsController": true,
    "Order": 0,
    "Parameters": [
      {
        "Name": "id",
        "Type": "System.Int32",
        "IsRequired": true
      }
    ],
    "ReturnTypes": []
  },
  {
    "ContainingType": "BookMyShowBackend.Controllers.BookMyShowController",
    "Method": "GetShows",
    "RelativePath": "api/movies/slots/{id}",
    "HttpMethod": "GET",
    "IsController": true,
    "Order": 0,
    "Parameters": [
      {
        "Name": "id",
        "Type": "System.Int32",
        "IsRequired": true
      }
    ],
    "ReturnTypes": []
  },
  {
    "ContainingType": "BookMyShowBackend.Controllers.BookMyShowController",
    "Method": "CreateShow",
    "RelativePath": "api/movies/slots/create",
    "HttpMethod": "POST",
    "IsController": true,
    "Order": 0,
    "Parameters": [
      {
        "Name": "showDto",
        "Type": "BookMyShowBackend.DTO.ShowsDTO",
        "IsRequired": true
      }
    ],
    "ReturnTypes": []
  },
  {
    "ContainingType": "BookMyShowBackend.Controllers.BookMyShowController",
    "Method": "UpdateShow",
    "RelativePath": "api/movies/slots/update/{id}",
    "HttpMethod": "PUT",
    "IsController": true,
    "Order": 0,
    "Parameters": [
      {
        "Name": "id",
        "Type": "System.Int32",
        "IsRequired": true
      },
      {
        "Name": "updatedShow",
        "Type": "BookMyShowBackend.Models.Shows",
        "IsRequired": true
      }
    ],
    "ReturnTypes": []
  },
  {
    "ContainingType": "BookMyShowBackend.Controllers.BookMyShowController",
    "Method": "UpdateMovie",
    "RelativePath": "api/movies/update/{id}",
    "HttpMethod": "PUT",
    "IsController": true,
    "Order": 0,
    "Parameters": [
      {
        "Name": "id",
        "Type": "System.Int32",
        "IsRequired": true
      },
      {
        "Name": "updatedMovie",
        "Type": "BookMyShowBackend.Models.Movie",
        "IsRequired": true
      }
    ],
    "ReturnTypes": []
  },
  {
    "ContainingType": "BookMyShowBackend.Controllers.BookMyShowController",
    "Method": "GetSlotById",
    "RelativePath": "api/slot/{id}",
    "HttpMethod": "GET",
    "IsController": true,
    "Order": 0,
    "Parameters": [
      {
        "Name": "id",
        "Type": "System.Int32",
        "IsRequired": true
      }
    ],
    "ReturnTypes": []
  },
  {
    "ContainingType": "BookMyShowBackend.Controllers.BookMyShowController",
    "Method": "CreateBooking",
    "RelativePath": "api/ticket",
    "HttpMethod": "POST",
    "IsController": true,
    "Order": 0,
    "Parameters": [
      {
        "Name": "request",
        "Type": "BookMyShowBackend.DTO.TicketDTO",
        "IsRequired": true
      }
    ],
    "ReturnTypes": []
  },
  {
    "ContainingType": "BookMyShowBackend.Controllers.BookMyShowController",
    "Method": "GetAllUsers",
    "RelativePath": "api/users",
    "HttpMethod": "GET",
    "IsController": true,
    "Order": 0,
    "Parameters": [],
    "ReturnTypes": []
  },
  {
    "ContainingType": "BookMyShowBackend.Controllers.BookMyShowController",
    "Method": "GetUserById",
    "RelativePath": "api/users/{id}",
    "HttpMethod": "GET",
    "IsController": true,
    "Order": 0,
    "Parameters": [
      {
        "Name": "id",
        "Type": "System.Int32",
        "IsRequired": true
      }
    ],
    "ReturnTypes": []
  }
]